Metadata-Version: 2.1
Name: pyduckgo
Version: 0.2.0
Summary: Simple async wrapper for DuckDuckGo
Home-page: https://github.com/jDan735/pyduckgo
Author: Daniel Zakharov
Author-email: daniel734@bk.ru
License: MIT
Keywords: api duckduckgo python
Platform: UNKNOWN
Classifier: Programming Language :: Python :: 3.5
Classifier: Programming Language :: Python :: 3.6
Classifier: Programming Language :: Python :: 3.7
Classifier: Programming Language :: Python :: 3.8
Classifier: License :: OSI Approved :: MIT License
Requires-Python: >=3
